[
  {
    "author": "Syzlak",
    "date": "2009-08-14T14:16:19",
    "body": "Check out Justin King sometime on YouTube too. He's a slap player that does a lot of tap melody work. It's not necessarily my favorite stuff in the world, but it's very good. I'd link to something, but the quality is so poor…old videos from 2 years ago\n\nThink about that. YouTube videos from only 2 years ago are being deemed “poor.” 2 years…",
    "reply_to": null
  },
  {
    "author": "Syzlak",
    "date": "2009-08-14T14:16:56",
    "body": "ahh screw it – [http://www.youtube.com/watch?v=QF4IThskAtQ](http://www.youtube.com/watch?v=QF4IThskAtQ)",
    "reply_to": null
  },
  {
    "author": "Matt Burgess",
    "date": "2009-08-17T22:36:38",
    "body": "What. the. hell. Dude is insane.  \nAgree with what you say, not necessarily the easiest stuff to listen to (not easy at all, really)… but totally, completely insane.",
    "reply_to": null
  },
  {
    "author": "Matt Burgess",
    "date": "2009-08-18T05:36:38",
    "body": "What. the. hell. Dude is insane.  \nAgree with what you say, not necessarily the easiest stuff to listen to (not easy at all, really)… but totally, completely insane.",
    "reply_to": null
  }
]
