[
  {
    "author": "Matt Wardlaw",
    "date": "2008-05-16T02:01:44",
    "body": "I wasn’t quite sure what to expect from this album….from the 9 minute long lead single…but like you, I was happy as well!\n\nGood stuff!",
    "reply_to": null
  },
  {
    "author": "Burgo",
    "date": "2008-05-16T03:15:18",
    "body": "Great minds obviously think alike Matt :)",
    "reply_to": null
  },
  {
    "author": "Kalena",
    "date": "2008-05-18T09:49:06",
    "body": "Ice is Getting Thinner – such a haunting, poignant song \\*sniff\\*. Might have to buy this album, thanks for the sample Burgo",
    "reply_to": null
  },
  {
    "author": "Burgo",
    "date": "2008-05-18T21:31:51",
    "body": "@ Kalena,\n\nThanks for dropping by! It’s a killer track, isn’t it? That last time that Ben Gibbard plaintively sings:\n\n> “Then it saddens me to say what we both knew was true  \n> That the ice was getting thinner under me and you”\n\n… man, it just gets me.",
    "reply_to": null
  },
  {
    "author": "Kalena",
    "date": "2008-05-19T09:40:15",
    "body": "@ admin – ditto. I love musicians who totally nail timing and understatement",
    "reply_to": null
  }
]
