[
  {
    "author": "Matt Wardlaw",
    "date": "2008-06-21T15:57:20",
    "body": "good stuff, yo – thanks for hipping me to Joe’s stuff!",
    "reply_to": null
  },
  {
    "author": "Kalena",
    "date": "2008-07-28T02:37:58",
    "body": "Impressive! But he sounds so much older than he looks :-)",
    "reply_to": null
  },
  {
    "author": "Burgo",
    "date": "2008-07-28T02:44:07",
    "body": "Hey Kalena,  \nThanks for stopping by! Yeah, there’s definitely a wealth of wisdom there in this kid… despite his only 23 years of age.\n\nImagine it. I mean, this is impressive stuff _now_… I just can’t wait to see what Joe Pug produces when he hits 30! :P",
    "reply_to": null
  },
  {
    "author": "Shane",
    "date": "2008-07-28T04:39:02",
    "body": "Nice tunes Burgo… I like this guys style!",
    "reply_to": null
  }
]
